ELDB/__init__.py
ELDB/utils/__init__.py
ELDB/utils/utils.py
eldb-1.3.2.dist-info/METADATA
eldb-1.3.2.dist-info/WHEEL
eldb-1.3.2.dist-info/top_level.txt
eldb-1.3.2.dist-info/RECORD
